aiohttp_auth/__init__.py
aiohttp_auth/permissions.py
aiohttp_auth/acl/__init__.py
aiohttp_auth/acl/acl.py
aiohttp_auth/acl/decorators.py
aiohttp_auth/auth/__init__.py
aiohttp_auth/auth/abstract_auth.py
aiohttp_auth/auth/auth.py
aiohttp_auth/auth/cookie_ticket_auth.py
aiohttp_auth/auth/decorators.py
aiohttp_auth/auth/session_ticket_auth.py
aiohttp_auth/auth/ticket_auth.py
aiohttp_auth-0.1.1.dist-info/DESCRIPTION.rst
aiohttp_auth-0.1.1.dist-info/METADATA
aiohttp_auth-0.1.1.dist-info/RECORD
aiohttp_auth-0.1.1.dist-info/WHEEL
aiohttp_auth-0.1.1.dist-info/metadata.json
aiohttp_auth-0.1.1.dist-info/top_level.txt
