Metadata-Version: 1.1
Name: aiohttp_auth
Version: 0.1.1
Summary: Authorization and authentication middleware plugin for aiohttp.
Home-page: https://github.com/gnarlychicken/aiohttp_auth
Author: Gnarly Chicken
Author-email: gnarlychicken@gmx.com
License: MIT
Platform: UNKNOWN
Classifier: Development Status :: 3 - Alpha
Classifier: Intended Audience :: Developers
Classifier: Topic :: Internet :: WWW/HTTP :: Session
Classifier: License :: OSI Approved :: MIT License
Classifier: Programming Language :: Python :: 3 :: Only
Classifier: Programming Language :: Python :: 3.5
